flask_wtf_alchemy_utils.py
flask_wtf_alchemy_utils-0.1.0.dist-info/RECORD
flask_wtf_alchemy_utils-0.1.0.dist-info/DESCRIPTION.rst
flask_wtf_alchemy_utils-0.1.0.dist-info/top_level.txt
flask_wtf_alchemy_utils-0.1.0.dist-info/METADATA
flask_wtf_alchemy_utils-0.1.0.dist-info/WHEEL
flask_wtf_alchemy_utils-0.1.0.dist-info/metadata.json
