Metadata-Version: 2.0
Name: flask-wtf-alchemy-utils
Version: 0.1.0
Summary: Form and field utility base classes for use with Flask, Flask-WTF, and wtforms-alchemy.
Home-page: https://github.com/Jaza/flask-wtf-alchemy-utils
Author: Jeremy Epstein
Author-email: jazepstein@gmail.com
License: UNKNOWN
Platform: any
Classifier: Development Status :: 2 - Pre-Alpha
Classifier: Environment :: Web Environment
Classifier: Intended Audience :: Developers
Classifier: Operating System :: OS Independent
Classifier: Programming Language :: Python
Classifier: Programming Language :: Python :: 2
Classifier: Programming Language :: Python :: 2.7
Classifier: Programming Language :: Python :: 3
Classifier: Programming Language :: Python :: 3.3
Requires-Dist: Flask
Requires-Dist: Flask-WTF
Requires-Dist: WTForms-Alchemy
